ikvpy/__about__.py
ikvpy/__init__.py
ikvpy/bin_manager.py
ikvpy/client.py
ikvpy/clientoptions.py
ikvpy/document.py
ikvpy/factory.py
ikvpy/native_reader.py
ikvpy/reader.py
ikvpy/utils.py
ikvpy/writer.py
ikvpy/schemas/__init__.py
ikvpy/schemas/common_pb2.py
ikvpy/schemas/common_pb2.pyi
ikvpy/schemas/common_pb2_grpc.py
ikvpy/schemas/services_pb2.py
ikvpy/schemas/services_pb2.pyi
ikvpy/schemas/services_pb2_grpc.py
ikvpy/schemas/streaming_pb2.py
ikvpy/schemas/streaming_pb2.pyi
ikvpy/schemas/streaming_pb2_grpc.py
ikvpy-0.0.36.dist-info/METADATA
ikvpy-0.0.36.dist-info/WHEEL
ikvpy-0.0.36.dist-info/licenses/LICENSE
ikvpy-0.0.36.dist-info/RECORD
